CNery/__init__.py
CNery/core.py
CNery/get_CNV.py
cnery-1.0.2.dist-info/licenses/LICENSE
cnery-1.0.2.dist-info/METADATA
cnery-1.0.2.dist-info/WHEEL
cnery-1.0.2.dist-info/entry_points.txt
cnery-1.0.2.dist-info/top_level.txt
cnery-1.0.2.dist-info/RECORD
